{
  "headers": {
    "content-type": "application/typescript; charset=utf-8",
    "etag": "\"7034b0b6bae74081e513a177f8328525\"",
    "content-security-policy": "default-src 'none'; style-src 'unsafe-inline'; sandbox",
    "x-amz-cf-id": "s8xwCej_RbXL9NHK3d7O6z5XiPeCZL9lsI3E86e7Zy5sbth007c3Dw==",
    "last-modified": "Thu, 04 Jan 2024 19:29:46 GMT",
    "referrer-policy": "strict-origin-when-cross-origin",
    "x-amz-version-id": "aHPKqIZXGbHwxD.XygiaSi7WT2eB0X6l",
    "x-content-type-options": "nosniff",
    "cache-control": "public, max-age=31536000, immutable",
    "cross-origin-embedder-policy": "same-origin",
    "cross-origin-resource-policy": "same-origin",
    "x-frame-options": "DENY",
    "server-timing": "fetchSource;dur=10",
    "access-control-allow-origin": "*",
    "content-length": "2613",
    "server": "deno/gcp-europe-west3",
    "vary": "Accept-Encoding, Origin",
    "accept-ranges": "bytes",
    "x-amz-cf-pop": "FRA56-P5",
    "age": "10246454",
    "cross-origin-opener-policy": "same-origin",
    "date": "Mon, 15 Jan 2024 22:36:41 GMT",
    "x-amz-replication-status": "COMPLETED",
    "x-amz-server-side-encryption": "AES256",
    "strict-transport-security": "max-age=63072000; includeSubDomains; preload",
    "x-cache": "Hit from cloudfront",
    "via": "http/2 edgeproxy-h"
  },
  "url": "https://deno.land/std@0.211.0/encoding/base64.ts",
  "now": {
    "secs_since_epoch": 1715604654,
    "nanos_since_epoch": 943072597
  }
}